gawseed_tcorex/__init__.py
gawseed_tcorex/base.py
gawseed_tcorex/corex.py
gawseed_tcorex/covariance.py
gawseed_tcorex/plot_utils.py
gawseed_tcorex/tcorex.py
gawseed_tcorex/tcorex_learnable.py
gawseed_tcorex/experiments/__init__.py
gawseed_tcorex/experiments/baselines.py
gawseed_tcorex/experiments/data.py
gawseed_tcorex/experiments/fmri_utils.py
gawseed_tcorex/experiments/misc.py
gawseed_tcorex/experiments/vis_utils.py
gawseed_tcorex/tools/__init__.py
gawseed_tcorex/tools/tcorex_changepoints.py
gawseed_tcorex/tools/tcorex_cli.py
gawseed_tcorex/tools/tcorex_plot.py
gawseed_tcorex-1.1.1.dist-info/METADATA
gawseed_tcorex-1.1.1.dist-info/WHEEL
gawseed_tcorex-1.1.1.dist-info/entry_points.txt
gawseed_tcorex-1.1.1.dist-info/licenses/LICENSE
gawseed_tcorex-1.1.1.dist-info/RECORD
