Metadata-Version: 2.3
Name: gawseed-tcorex
Version: 1.1.1
Summary: Correlation Explanation Methods
Project-URL: Homepage, https://github.com/gawseed/T-CorEx
Author-email: Hrayr Harutyunyan <harhro@gmail.com>
License-Expression: AGPL-3.0
License-File: LICENSE
Classifier: Intended Audience :: Science/Research
Classifier: Programming Language :: Python :: 3
Classifier: Programming Language :: Python :: 3.7
Classifier: Programming Language :: Python :: 3.8
Classifier: Programming Language :: Python :: 3.9
Classifier: Programming Language :: Python :: 3.10
Classifier: Programming Language :: Python :: 3.11
Classifier: Programming Language :: Python :: 3.12
Classifier: Topic :: Scientific/Engineering :: Artificial Intelligence
Classifier: Topic :: Scientific/Engineering :: Information Analysis
Classifier: Topic :: Scientific/Engineering :: Mathematics
Requires-Dist: linearcorex==0.52
Requires-Dist: matplotlib>=2.2.2
Requires-Dist: nibabel>=2.3.1
Requires-Dist: nilearn>=0.4.2
Requires-Dist: nose>=1.3.7
Requires-Dist: numpy>=1.14.2
Requires-Dist: pandas>=0.23.4
Requires-Dist: regain==0.1.7
Requires-Dist: scikit-learn
Requires-Dist: scikit-learn>=0.20.0
Requires-Dist: scipy>=1.1.0
Requires-Dist: torch>=1.0
Requires-Dist: tqdm>=4.26
